gfe_examples/__init__.py
gfe_examples/Conways/__init__.py
gfe_examples/Conways/no_edges_examples/__init__.py
gfe_examples/Conways/no_edges_examples/conways_basic_cell.py
gfe_examples/Conways/no_edges_examples/conways_no_edges.py
gfe_examples/Conways/one_no_graph_example/__init__.py
gfe_examples/Conways/one_no_graph_example/conways_no_graph.py
gfe_examples/Conways/one_no_graph_example/spiNNakerGraphFrontEnd.cfg
gfe_examples/Conways/partitioned_example_a_no_vis_no_buffer/__init__.py
gfe_examples/Conways/partitioned_example_a_no_vis_no_buffer/conways_basic_cell.py
gfe_examples/Conways/partitioned_example_a_no_vis_no_buffer/conways_partitioned.py
gfe_examples/Conways/partitioned_example_b_no_vis_buffer/__init__.py
gfe_examples/Conways/partitioned_example_b_no_vis_buffer/conways_basic_cell.py
gfe_examples/Conways/partitioned_example_b_no_vis_buffer/conways_partitioned.py
gfe_examples/hello_world/__init__.py
gfe_examples/hello_world/hello_world.py
gfe_examples/hello_world/hello_world_vertex.py
gfe_examples/hello_world_untimed/__init__.py
gfe_examples/hello_world_untimed/hello_world.py
gfe_examples/hello_world_untimed/hello_world_vertex.py
gfe_examples/live_io/__init__.py
gfe_examples/live_io/live_io.py
gfe_examples/live_io/live_io_vertex.py
gfe_examples/sync_test/__init__.py
gfe_examples/sync_test/sync_test.py
gfe_examples/sync_test/sync_test_vertex.py
gfe_examples/template/__init__.py
gfe_examples/template/python_template.py
gfe_examples/template/template_vertex.py
gfe_integration_tests/__init__.py
gfe_integration_tests/script_builder.py
gfe_integration_tests/test_hello_world.py
gfe_integration_tests/test_hello_world_untimed.py
gfe_integration_tests/test_scripts.py
gfe_integration_tests/sdram_edge_tests/__init__.py
gfe_integration_tests/sdram_edge_tests/common/__init__.py
gfe_integration_tests/sdram_edge_tests/common/sdram_machine_vertex.py
gfe_integration_tests/sdram_edge_tests/common/sdram_test_vertex.py
spinnakergraphfrontend-1!7.4.1.dist-info/licenses/LICENSE
spinnakergraphfrontend-1!7.4.1.dist-info/licenses/LICENSE_POLICY.md
spinnakergraphfrontend-1!7.4.1.dist-info/METADATA
spinnakergraphfrontend-1!7.4.1.dist-info/WHEEL
spinnakergraphfrontend-1!7.4.1.dist-info/top_level.txt
spinnakergraphfrontend-1!7.4.1.dist-info/zip-safe
spinnakergraphfrontend-1!7.4.1.dist-info/RECORD
